cfg/__init__.py
predictor/__init__.py
predictor/predictor.py
predictor/example_predictor/__init__.py
predictor/example_predictor/example_predictor.py
predictor/mowgli_predictor/__init__.py
predictor/mowgli_predictor/mowgli_predictor.py
tests/__init__.py
tests/ground.py
utils/__init__.py
utils/general.py
mowgli_in_the_jungle-1.0.0.dist-info/METADATA
mowgli_in_the_jungle-1.0.0.dist-info/WHEEL
mowgli_in_the_jungle-1.0.0.dist-info/top_level.txt
mowgli_in_the_jungle-1.0.0.dist-info/RECORD
