Metadata-Version: 2.1
Name: mowgli-in-the-jungle
Version: 1.0.0
Summary: Commonsense framework
Home-page: https://github.com/usc-isi-i2/mowgli-in-the-jungle
Author: Filip Ilievski
Author-email: ilievski@isi.edu
License: UNKNOWN
Platform: UNKNOWN
Classifier: Programming Language :: Python :: 3
Classifier: License :: OSI Approved :: MIT License
Classifier: Operating System :: OS Independent
Requires-Dist: pandas (==0.25.1)
Requires-Dist: loguru (==0.4.1)
Requires-Dist: tqdm (==4.36.1)
Requires-Dist: scipy (==1.3.1)
Requires-Dist: numpy (==1.17.2)
Requires-Dist: PyYAML (==5.3)
Requires-Dist: scikit-learn (==0.22.1)
